HDL_description/src/program_counter.v
module program_counter(clk, reset, addition, count);

   //Inputs & outputs
   input wire clk, reset;
   input wire [11:0] addition;
   output reg [11:0] count;
   
   //Functional block
   integer set = 0;
   
   always @(posedge clk)
   begin
      if (reset)
      begin
         count <= 12'bx;
         set <= 0;
      end
      else if (set==1)
         count <= count + addition;
      else
      begin
         count <= 12'b000000000000;
         set <= 1;
      end
   end
endmodule

HDL_description/program_counter/program_counter_tb.v
`include "program_counter.v"
`timescale 1ns/1ns

module program_counter_tb();

   reg clk, reset;
   reg [11:0] addition;
   wire [11:0] count;
   
   program_counter DUT (.clk(clk),
                        .reset(reset),
                        .addition(addition),
                        .count(count));
   initial
   begin
      $dumpfile("program_counter.vcd");
      $dumpvars(0, program_counter_tb);
      
      reset = 1'b0;
      addition = 12'b000000000100;
      #60 reset = 1'b1;
      #20 reset = 1'b0;
      #40 $finish;
   end
   
   initial
   begin
      clk = 1'b0;
      forever #10 clk = ~clk;
   end
endmodule

HDL_description/program_counter/program_counter.vcd
$date
	Sat Oct 14 14:29:38 2023
$end
$version
	Icarus Verilog
$end
$timescale
	1ns
$end
$scope module program_counter_tb $end
$var wire 12 ! count [11:0] $end
$var reg 12 " addition [11:0] $end
$var reg 1 # clk $end
$var reg 1 $ reset $end
$scope module DUT $end
$var wire 12 % addition [11:0] $end
$var wire 1 # clk $end
$var wire 1 $ reset $end
$var reg 12 & count [11:0] $end
$var integer 32 ' set [31:0] $end
$upscope $end
$upscope $end
$enddefinitions $end
$comment Show the parameter values. $end
$dumpall
$end
#0
$dumpvars
b0 '
bx &
b100 %
0$
0#
b100 "
bx !
$end
#10
b1 '
b0 !
b0 &
1#
#20
0#
#30
b100 !
b100 &
1#
#40
0#
#50
b1000 !
b1000 &
1#
#60
0#
1$
#70
b0 '
bx !
bx &
1#
#80
0#
0$
#90
b1 '
b0 !
b0 &
1#
#100
0#
#110
b100 !
b100 &
1#
