OPENLANE_digital_flow/alu/src/alu.v
module alu(control, data_in1, data_in2, data_out);

   //Inputs & outputs
   input wire [3:0] control;
   input wire [31:0] data_in1, data_in2;
   output reg [31:0] data_out;

   //Functional block   
   always @*
      case (control)
         4'b0000: data_out = data_in1 + data_in2; //add
         4'b0001: data_out = data_in1 - data_in2; //sub
         4'b0010: data_out = data_in1 << data_in2; //sll
         4'b0100: data_out = ($signed(data_in1) < $signed(data_in2))? 32'h00000001:32'h00000000; //slt
         4'b0110: data_out = (data_in1 < data_in2)? 32'h00000001:32'h00000000; //sltu
         4'b1000: data_out = data_in1 ^ data_in2; //xor
         4'b1010: data_out = data_in1 >> data_in2; //slr
         4'b1011: data_out = $signed(data_in1) >>> data_in2; //sra
         4'b1100: data_out = data_in1 | data_in2; //or
         4'b1110: data_out = data_in1 & data_in2; //and
         4'b0111: data_out = (data_in1 == data_in2)? 32'h00000001:32'h00000000; //seq
         default: data_out = 32'hxxxxxxxx;
      endcase
endmodule

HDL_description/alu/alu_tb.v
`include "alu.v"
`timescale 1ns/1ns

module alu_tb();

   reg [3:0] control;
   reg [31:0] data_in1, data_in2;
   wire [31:0] data_out;
   
   alu DUT (.control(control),
            .data_in1(data_in1),
            .data_in2(data_in2),
            .data_out(data_out));
   
   initial
   begin
      $dumpfile("alu.vcd");
      $dumpvars(0, alu_tb);
   
      control = 4'b0000;
      data_in1 = 32'h00000006;
      data_in2 = 32'h00000002;
      
      #10 control = 4'b0001;
      #10 control = 4'b1110;
      #10 control = 4'b1100;
      #10 control = 4'b1000;
      #10 control = 4'b0010;
      #10 control = 4'b1010;
      #10 control = 4'b1011; data_in1 = 32'hF0000006;
      #10 control = 4'b0100;
      #10 control = 4'b0110;
      #10 control = 4'b1111;
      #10 control = 4'b0111;
      #10 $finish;
   end
endmodule

HDL_description/alu/alu.vcd
$date
	Sat Oct 14 13:43:35 2023
$end
$version
	Icarus Verilog
$end
$timescale
	1ns
$end
$scope module alu_tb $end
$var wire 32 ! data_out [31:0] $end
$var reg 4 " control [3:0] $end
$var reg 32 # data_in1 [31:0] $end
$var reg 32 $ data_in2 [31:0] $end
$scope module DUT $end
$var wire 4 % control [3:0] $end
$var wire 32 & data_in1 [31:0] $end
$var wire 32 ' data_in2 [31:0] $end
$var reg 32 ( data_out [31:0] $end
$upscope $end
$upscope $end
$enddefinitions $end
$comment Show the parameter values. $end
$dumpall
$end
#0
$dumpvars
b1000 (
b10 '
b110 &
b0 %
b10 $
b110 #
b0 "
b1000 !
$end
#10
b100 !
b100 (
b1 "
b1 %
#20
b10 !
b10 (
b1110 "
b1110 %
#30
b110 !
b110 (
b1100 "
b1100 %
#40
b100 !
b100 (
b1000 "
b1000 %
#50
b11000 !
b11000 (
b10 "
b10 %
#60
b1 !
b1 (
b1010 "
b1010 %
#70
b11111100000000000000000000000001 !
b11111100000000000000000000000001 (
b11110000000000000000000000000110 #
b11110000000000000000000000000110 &
b1011 "
b1011 %
#80
b1 !
b1 (
b100 "
b100 %
#90
b0 !
b0 (
b110 "
b110 %
#100
bx !
bx (
b1111 "
b1111 %
#110
b0 !
b0 (
b111 "
b111 %
